kicad_pcb_api/README.md
kicad_pcb_api/__init__.py
kicad_pcb_api/py.typed
kicad_pcb_api/core/__init__.py
kicad_pcb_api/core/pcb_board.py
kicad_pcb_api/core/pcb_formatter.py
kicad_pcb_api/core/pcb_parser.py
kicad_pcb_api/core/types.py
kicad_pcb_api/footprints/__init__.py
kicad_pcb_api/footprints/footprint_library.py
kicad_pcb_api/mcp/__init__.py
kicad_pcb_api/mcp/server.py
kicad_pcb_api/placement/__init__.py
kicad_pcb_api/placement/base.py
kicad_pcb_api/placement/bbox.py
kicad_pcb_api/placement/courtyard_collision.py
kicad_pcb_api/placement/hierarchical_placement.py
kicad_pcb_api/placement/spiral_placement.py
kicad_pcb_api/placement/utils.py
kicad_pcb_api/routing/CHANGELOG.md
kicad_pcb_api/routing/FREEROUTING_SETUP.md
kicad_pcb_api/routing/__init__.py
kicad_pcb_api/routing/dsn_exporter.py
kicad_pcb_api/routing/freerouting_docker.py
kicad_pcb_api/routing/freerouting_runner.py
kicad_pcb_api/routing/install_freerouting.py
kicad_pcb_api/routing/ses_importer.py
kicad_pcb_api/utils/__init__.py
kicad_pcb_api/utils/kicad_cli.py
kicad_pcb_api/utils/validation.py
kicad_pcb_api-0.0.1.dist-info/METADATA
kicad_pcb_api-0.0.1.dist-info/WHEEL
kicad_pcb_api-0.0.1.dist-info/entry_points.txt
kicad_pcb_api-0.0.1.dist-info/licenses/LICENSE
kicad_pcb_api-0.0.1.dist-info/RECORD
