Metadata-Version: 2.4
Name: kicad-pcb-api
Version: 0.0.1
Summary: Professional KiCAD PCB Manipulation Library with File-Based Operations
Project-URL: Homepage, https://github.com/circuit-synth/kicad-pcb-api
Project-URL: Documentation, https://kicad-pcb-api.readthedocs.io
Project-URL: Repository, https://github.com/circuit-synth/kicad-pcb-api
Project-URL: Issues, https://github.com/circuit-synth/kicad-pcb-api/issues
Author-email: Circuit-Synth Team <contact@circuit-synth.com>
License-Expression: MIT
License-File: LICENSE
Keywords: ai-integration,automation,circuit-design,eda,electronics,kicad,pcb,placement,routing
Classifier: Development Status :: 3 - Alpha
Classifier: Intended Audience :: Developers
Classifier: Intended Audience :: Science/Research
Classifier: License :: OSI Approved :: MIT License
Classifier: Operating System :: OS Independent
Classifier: Programming Language :: Python :: 3
Classifier: Programming Language :: Python :: 3.10
Classifier: Programming Language :: Python :: 3.11
Classifier: Programming Language :: Python :: 3.12
Classifier: Topic :: Scientific/Engineering :: Electronic Design Automation (EDA)
Classifier: Topic :: Software Development :: Libraries :: Python Modules
Requires-Python: >=3.10
Requires-Dist: loguru>=0.7.0
Requires-Dist: sexpdata>=0.0.3
Provides-Extra: dev
Requires-Dist: black>=23.0.0; extra == 'dev'
Requires-Dist: mypy>=1.7.0; extra == 'dev'
Requires-Dist: pytest-cov>=4.0.0; extra == 'dev'
Requires-Dist: pytest>=7.0.0; extra == 'dev'
Requires-Dist: ruff>=0.1.0; extra == 'dev'
Provides-Extra: mcp
Requires-Dist: mcp>=1.0.0; extra == 'mcp'
Provides-Extra: routing
Requires-Dist: docker>=6.0.0; extra == 'routing'
Requires-Dist: requests>=2.31.0; extra == 'routing'
